MANIFEST.in
README.rst
setup.py
usfm/__init__.py
usfm/config.py
usfm/html.py
usfm/log.py
usfm/main.py
usfm.egg-info/PKG-INFO
usfm.egg-info/SOURCES.txt
usfm.egg-info/dependency_links.txt
usfm.egg-info/entry_points.txt
usfm.egg-info/not-zip-safe
usfm.egg-info/requires.txt
usfm.egg-info/top_level.txt
usfm/html_templates/template.html